[
  {
    "ss58": "dmxjZSec4Xj3xz3nBEwSHjQSnRGhvcoB4eRabkiw7pSDuv8fW",
    "status": "invulnerable",
    "metrics": {
      "calamari": "https://para.metrics.crispy.calamari.systems",
      "kusama": "https://relay.metrics.crispy.calamari.systems"
    },
    "balance": {
      "nonce": "0",
      "tokenSymbol": "KMA",
      "free": "23208254333693424",
      "reserved": "0",
      "miscFrozen": "0",
      "feeFrozen": "0",
      "locks": []
    },
    "session": {
      "aura": "0x7c4e5ea112f816c85f2bc77383cca50b73af038e327d39dca94252a4553b897e"
    }
  },
  {
    "ss58": "dmu63DLez715hRyhzdigz6akxS2c9W6RQvrToUWuQ1hntcBwF",
    "status": "invulnerable",
    "metrics": {
      "calamari": "https://para.metrics.crunchy.calamari.systems",
      "kusama": "https://relay.metrics.crunchy.calamari.systems"
    },
    "balance": {
      "nonce": "0",
      "tokenSymbol": "KMA",
      "free": "24097887852894765",
      "reserved": "0",
      "miscFrozen": "0",
      "feeFrozen": "0",
      "locks": []
    },
    "session": {
      "aura": "0xe6cd4aa48cfb4638c90b2b4965e28f6f0eabdc261c545a31917243ad7c45d633"
    }
  },
  {
    "ss58": "dmxvivs72h11DBNyKbeF8KQvcksoZsK9uejLpaWygFHZ2fU9z",
    "status": "invulnerable",
    "metrics": {
      "calamari": "https://para.metrics.hotdog.calamari.systems",
      "kusama": "https://relay.metrics.hotdog.calamari.systems"
    },
    "balance": {
      "nonce": "0",
      "tokenSymbol": "KMA",
      "free": "24163734364202277",
      "reserved": "0",
      "miscFrozen": "0",
      "feeFrozen": "0",
      "locks": []
    },
    "session": {
      "aura": "0xba3ca0dcf9e7515da2ad6ad37aba358ac8dfc727d791f6607d5779f934323859"
    }
  },
  {
    "ss58": "dmyhGnuox8ny9R1efVsWKxNU2FevMxcPZaB66uEJqJhgC4a1W",
    "status": "invulnerable",
    "metrics": {
      "calamari": "https://para.metrics.tasty.calamari.systems",
      "kusama": "https://relay.metrics.tasty.calamari.systems"
    },
    "balance": {
      "nonce": "0",
      "tokenSymbol": "KMA",
      "free": "23675896454269085",
      "reserved": "0",
      "miscFrozen": "0",
      "feeFrozen": "0",
      "locks": []
    },
    "session": {
      "aura": "0xae06f5c31189ad71a94c3dee0e462619694db71821467dbe3d49ab06319add18"
    }
  },
  {
    "ss58": "dmzbLejekGYZmfo5FoSznv5bBik7vGowuLxvzqFs2gZo2kANh",
    "status": "invulnerable",
    "metrics": {
      "calamari": "https://para.metrics.tender.calamari.systems",
      "kusama": "https://relay.metrics.tender.calamari.systems"
    },
    "balance": {
      "nonce": "0",
      "tokenSymbol": "KMA",
      "free": "23170853880527940",
      "reserved": "0",
      "miscFrozen": "0",
      "feeFrozen": "0",
      "locks": []
    },
    "session": {
      "aura": "0x6efd8d34a7139069ff8eb2cfe94af804a74f3084db80b6d052c0b5e300e78602"
    }
  },
  {
    "ss58": "dmu7rmwTa35Ec5cnNMpn8EpnFPA727sDtpCQwu9uCo2sfnmg1",
    "status": "active",
    "metrics": {
      "calamari": "https://calamari.metrics.novgorodian.thgttg.com",
      "kusama": "https://kusama.metrics.novgorodian.thgttg.com"
    },
    "balance": {
      "nonce": "2",
      "tokenSymbol": "KMA",
      "free": "495046729726711",
      "reserved": "400000000000000000",
      "miscFrozen": "0",
      "feeFrozen": "0",
      "locks": []
    },
    "session": {
      "aura": "0xd6856ad2ead4d66746c02e49b56ada447bc4f91bc598f0592af2182e1ce34b54"
    }
  },
  {
    "ss58": "dmvvqrfK5AUYH294zTCCiimJRV7CQDDQyC7RAkd5aZgUn9S6f",
    "status": "active",
    "metrics": {
      "calamari": "http://65.108.122.7:9615",
      "kusama": "http://65.108.122.7:9616"
    },
    "balance": {
      "nonce": "4",
      "tokenSymbol": "KMA",
      "free": "10339241121518445",
      "reserved": "400000000000000000",
      "miscFrozen": "10000000000000000",
      "feeFrozen": "0",
      "locks": [
        {
          "id": "0x64656d6f63726163",
          "amount": "10000000000000000",
          "reasons": "Misc"
        }
      ]
    },
    "session": {
      "aura": "0x3c8bc4b3518ce7a15c75ca02d86b0a6dadd6dcf721249df69340815a35cb240d"
    }
  },
  {
    "ss58": "dmvoKqM8n2PVKyiYhm5VpMMnzMdk1z1WZAYDJEDmSLSqRgrbQ",
    "status": "active",
    "metrics": {
      "calamari": "https://calamari.metrics.polkadotters.com",
      "kusama": "https://kusama.metrics.polkadotters.com"
    },
    "balance": {
      "nonce": "3",
      "tokenSymbol": "KMA",
      "free": "279704285748448",
      "reserved": "400000000000000000",
      "miscFrozen": "0",
      "feeFrozen": "0",
      "locks": []
    },
    "session": {
      "aura": "0x321ab38709b9940c72dcbe3f983c94b8ad6013e62387018c5b385c8168d3b410"
    }
  },
  {
    "ss58": "dmyhGCWjejSyze6Hcqx43f8PNR9RWwm4EEobo8HehtBb8W8aU",
    "status": "active",
    "metrics": {
      "calamari": "https://calamari.metrics.cj.kmapro.de",
      "kusama": "https://kusama.metrics.cj.kmapro.de"
    },
    "balance": {
      "nonce": "1",
      "tokenSymbol": "KMA",
      "free": "1189961076589850",
      "reserved": "400000000000000000",
      "miscFrozen": "0",
      "feeFrozen": "0",
      "locks": []
    },
    "session": {
      "aura": "0xe487137c1078d07d75c5e6d27fb5fa4b6b3584b01f003a9e23b88bc6734d0c74"
    }
  },
  {
    "ss58": "dmvPNCD8YaHusmrdtvpB6HG72BibVSpnbHugT893x4Hw9P186",
    "status": "active",
    "metrics": {
      "calamari": "https://calamari.metrics.calamari.stakecraft.com",
      "kusama": "https://kusama.metrics.calamari.stakecraft.com"
    },
    "balance": {
      "nonce": "2",
      "tokenSymbol": "KMA",
      "free": "10085951594160839",
      "reserved": "400000000000000000",
      "miscFrozen": "0",
      "feeFrozen": "0",
      "locks": []
    },
    "session": {
      "aura": "0xd21453f970e664168af721e1b42755cc8c556568ed4577c5e08b36036d6b4e0e"
    }
  },
  {
    "ss58": "dmzWDne3MxniVDcF4i2nGkfPZa4pfkWL1AXqgSvWgZmDoTcYw",
    "status": "active",
    "metrics": {
      "calamari": "https://calamari.metrics.dp.stakebaby.com",
      "kusama": "https://kusama.metrics.dp.stakebaby.com"
    },
    "balance": {
      "nonce": "7",
      "tokenSymbol": "KMA",
      "free": "219989331282158684",
      "reserved": "400000000000000000",
      "miscFrozen": "0",
      "feeFrozen": "0",
      "locks": []
    },
    "session": {
      "aura": "0xfc7b1017bb908017991e1f7d49455d17ca09667b25bc837076b021e43d636d53"
    }
  },
  {
    "ss58": "dmvFayQJ9S7BgbHE2kmnoVq9UfdbfwHpZ4d1revJfVA6X9dGR",
    "status": "active",
    "metrics": {
      "calamari": "https://stats.calamari.migusha.com",
      "kusama": "https://stats.kasuma.migusha.com"
    },
    "balance": {
      "nonce": "2",
      "tokenSymbol": "KMA",
      "free": "336255691735556055",
      "reserved": "400000000000000000",
      "miscFrozen": "0",
      "feeFrozen": "0",
      "locks": []
    },
    "session": {
      "aura": "0x7e59dd143f4382b415bf6893a3c95be69c8452f41d296f379a789ec60381173e"
    }
  },
  {
    "ss58": "dmu8uRzeiS7CjrKFiSU6bKMftbvJ16o6C4Z1yymQnQkCcrNou",
    "status": "active",
    "metrics": {
      "calamari": "https://calamari.pithecus.co.uk",
      "kusama": "https://kusama.pithecus.co.uk"
    },
    "balance": {
      "nonce": "24",
      "tokenSymbol": "KMA",
      "free": "3454201938042754",
      "reserved": "0",
      "miscFrozen": "2514050000000000",
      "feeFrozen": "0",
      "locks": [
        {
          "id": "0x63616c616d767374",
          "amount": "2514050000000000",
          "reasons": "Misc"
        },
        {
          "id": "0x64656d6f63726163",
          "amount": "2514050000000000",
          "reasons": "Misc"
        }
      ]
    }
  },
  {
    "ss58": "dmx7NaUig7rdhwTJcnj6VPFaeou4KsvTqkMTcvHz25LcZtNrT",
    "status": "active",
    "metrics": {
      "calamari": "https://calamari.brightlystake.com",
      "kusama": "https://kusama.brightlystake.com"
    },
    "balance": {
      "nonce": "3",
      "tokenSymbol": "KMA",
      "free": "50061814945144284",
      "reserved": "400000000000000000",
      "miscFrozen": "10000000000000000",
      "feeFrozen": "0",
      "locks": [
        {
          "id": "0x64656d6f63726163",
          "amount": "10000000000000000",
          "reasons": "Misc"
        }
      ]
    },
    "session": {
      "aura": "0xa2d852a507716444acd3576ef7eaaf2a8c59a7420953ebbd013c8919e8097958"
    }
  },
  {
    "ss58": "dmyEgR9K8hsgqt47XYnDDJJMaXgHnPLVjTFW8nfRa2RKoj17U",
    "status": "active",
    "metrics": {
      "calamari": "https://stats.calamari.themilkywaygang.com",
      "kusama": "https://stats.kasuma.themilkywaygang.com"
    },
    "balance": {
      "nonce": "2",
      "tokenSymbol": "KMA",
      "free": "1082230829977904",
      "reserved": "400000000000000000",
      "miscFrozen": "0",
      "feeFrozen": "0",
      "locks": []
    },
    "session": {
      "aura": "0x2c618e8a2dfcacde897443bb3316517b93a43395611e5d8ae7193e7c7c369e4d"
    }
  },
  {
    "ss58": "dmuomPgt6hJzKpDcEbz2BNNo9uPFXDvzBk7vnLQx6TLBQG85L",
    "metrics": {
      "calamari": "https://calamari.metrics.nettle.network",
      "kusama": "https://kusama.metrics.nettle.network"
    },
    "balance": {
      "nonce": "9",
      "tokenSymbol": "KMA",
      "free": "410074858578326963",
      "reserved": "0",
      "miscFrozen": "58000000000000000",
      "feeFrozen": "0",
      "locks": [
        {
          "id": "0x63616c616d767374",
          "amount": "58000000000000000",
          "reasons": "Misc"
        },
        {
          "id": "0x64656d6f63726163",
          "amount": "10000000000000000",
          "reasons": "Misc"
        }
      ]
    }
  },
  {
    "ss58": "dmuuG83f3JeXBmMp7e3XssJzq7rUAuNgAT3z7HoUPWueqpD1V",
    "metrics": {
      "calamari": "https://calamari.metrics.fundmybirthday.com",
      "kusama": "https://kusama.metrics.fundmybirthday.com"
    }
  },
  {
    "ss58": "dmww5oaqM52Tg9WHLe9WJ9bKhyekZH1SiT4mYdb2khY1zLQg6",
    "metrics": {
      "calamari": "https://calamari.metrics.substake.app",
      "kusama": "https://kusama.metrics.substake.app"
    }
  },
  {
    "ss58": "dmx4WhyUDhAjsMf1mRD55qApjxnqSXcSsmweHgcv8seGkrN4R",
    "metrics": {
      "calamari": "https://calamari.metrics.staker.space",
      "kusama": "https://kusama.metrics.staker.space"
    }
  },
  {
    "ss58": "dmxa3MJczFGT92BUQjwsxguUC2t5qFaDdagfpBQWdGkNPJYQ5",
    "metrics": {
      "calamari": "https://calamari.metrics.calamari.anonstake.com",
      "kusama": "https://kusama.metrics.calamari.anonstake.com"
    }
  },
  {
    "ss58": "dmzEUqQGSWsFewzpomYcjhLYkeSAvHYwEoKzG2yXcF8YQoJkL",
    "metrics": {
      "calamari": "https://calamari.metrics.favoursanywhere.com",
      "kusama": "https://kusama.metrics.favoursanywhere.com"
    }
  },
  {
    "ss58": "dmzUQzg7MjgxQDSA73hezRUBo3GysC42q4pxJE8qExy1CMMAm",
    "metrics": {
      "calamari": "https://calamari.rhee.substake.app",
      "kusama": "https://kusama.rhee.substake.app"
    }
  },
  {
    "ss58": "dmyxfU1bJM5UR5RWsypKm9KQDkVofm3ifp5gVjzs8uQHUmBZb",
    "metrics": {
      "calamari": "https://calamari.pathrocknetwork.org",
      "kusama": "https://kusama.pathrocknetwork.org"
    }
  },
  {
    "ss58": "dmvVY24KwgNwoYnHw5EbC8mTUF9CtZeJzCnSGBawWzaRkNHH4",
    "metrics": {
      "calamari": "https://calamari.metrics.letsnode.io",
      "kusama": "https://kusama.metrics.letsnode.io"
    }
  },
  {
    "ss58": "dmzh2ESTJAy1MJ8Ekg9zs1653HFBUqCQeErihJZSHfFXGgNUh",
    "metrics": {
      "calamari": "https://calamari.metrics.gostake.io",
      "kusama": "https://kusama.metrics.gostake.io"
    }
  },
  {
    "ss58": "dmynx7uZ8HE1gNSQhXiiqVrKX5yPkHka99HjfY98z8DqRtEw3",
    "metrics": {
      "calamari": "http://calamari.staking4all.org:9615",
      "kusama": "http://calamari.staking4all.org:9616"
    }
  },
  {
    "ss58": "dmuaG34aVnxirpMsHXu6Mg7RxNN3cxG74ZyjLVEgvzNqBXm2U",
    "metrics": {
      "calamari": "http://51.195.63.206:9615",
      "kusama": "http://51.195.63.206:9616"
    }
  },
  {
    "ss58": "dmvXcSGBjyW4cq3ban3L4LJB6RtHQhBmtztZZ4o6TYKjoZ7Ye",
    "metrics": {
      "calamari": "http://155.138.138.183:9615",
      "kusama": "http://155.138.138.183:9616"
    }
  },
  {
    "ss58": "dmyZopEVaerkgSWWTd4WScPkhQgHTeLfMcHVCkQUyL1gu29c3",
    "metrics": {
      "calamari": "https://calamari.metrics.rocke7.net",
      "kusama": "https://kusama.metrics.rocke7.net"
    }
  },
  {
    "ss58": "dmxbgDpKK6V3Sayr3jz8MpoUJyxiWese6FtL42RRfZXnWewTD",
    "metrics": {
      "calamari": "http://146.59.68.182:9615",
      "kusama": "http://146.59.68.182:9616"
    }
  },
  {
    "ss58": "dmvejwLsRVWLFNfWMm2potXvYU3TXBzxndun1zKqFRFs2nDP6",
    "metrics": {
      "calamari": "",
      "kusama": ""
    }
  },
  {
    "ss58": "dmvK7LAuPAAdSzFWqkXiS9AwxMhc7vCYmvZHg8iHveaFYG5HL",
    "metrics": {
      "calamari": "",
      "kusama": ""
    }
  },
  {
    "ss58": "dmwcJrQm4ShNd1ASnksCG465hchJKrjTGiSoFsC9vMJcgbsPV",
    "metrics": {
      "calamari": "",
      "kusama": ""
    }
  },
  {
    "ss58": "dmxARc22SyzyD29ca92pWkbcGjJcMibatAnAQnwEbo7zwiPFW",
    "metrics": {
      "calamari": "",
      "kusama": ""
    }
  },
  {
    "ss58": "dmy6WPM2KfD7WBxJYS6UG17GHJVCv8kewiwTr6ciVeXLbBpvf",
    "metrics": {
      "calamari": "",
      "kusama": ""
    }
  },
  {
    "ss58": "dmy9gzyanK9FpAxVamGa7TLz2t9RAn1SLzuy6fr5Pq5Sztqje",
    "metrics": {
      "calamari": "",
      "kusama": ""
    }
  },
  {
    "ss58": "dmyhNFR1qUuA8efaYvpW75qGKrYfzrK8ejygttHojeL4ujzUb",
    "metrics": {
      "calamari": "",
      "kusama": ""
    }
  },
  {
    "ss58": "dmyyAnvDKvWePe7d6yWzVnqVhJp9HbNMs5RDoKjUSABNQcVf5",
    "metrics": {
      "calamari": "",
      "kusama": ""
    }
  },
  {
    "ss58": "dmy6hUYKvUqpo7QxFFK5bgmnGYLpfSMxFDw2t3XpC6MjMkLJa",
    "metrics": {
      "calamari": "",
      "kusama": ""
    }
  },
  {
    "ss58": "dmzCAH7F9E6QoSuFWq2Hfq4b3XNzUz73zV82PzUiv4QUp5tH3",
    "metrics": {
      "calamari": "",
      "kusama": ""
    }
  },
  {
    "ss58": "dmv2KUDD1JHCgtYDSds8FUBf7bd59SLkGXLz979PV7V4DbX8G",
    "metrics": {
      "calamari": "",
      "kusama": ""
    }
  },
  {
    "ss58": "dmuBBGBxRRLhZa7QEfZvMPZsV3YXEgNeTkA1vhwhBhpLrSyH2",
    "metrics": {
      "calamari": "",
      "kusama": ""
    }
  },
  {
    "ss58": "dmud8aJzwQ5H8v1Zw9AekV8TXwEe412JCeCEcwKwsvkpeeCAU",
    "metrics": {
      "calamari": "",
      "kusama": ""
    }
  },
  {
    "ss58": "dmuMp3ZDzrggjgRmCsXLuriE2wB8qfAwhrwCskAsepqGnYyAD",
    "metrics": {
      "calamari": "",
      "kusama": ""
    }
  },
  {
    "ss58": "dmvQL8XfiJcfufCowNHCkJ8qxMAdw39i1nPsH8jf7AbEgnvNW",
    "metrics": {
      "calamari": "",
      "kusama": ""
    }
  },
  {
    "ss58": "dmvu53ayeLxRSf14ejMEBMpePQxSVwBDSvyQXC789miKprvgq",
    "metrics": {
      "calamari": "",
      "kusama": ""
    }
  },
  {
    "ss58": "dmwkmhm6YZgBihxdgvDLcwRy7ZuvzFDhEyntTYuy7QeXddxdN",
    "metrics": {
      "calamari": "",
      "kusama": ""
    }
  },
  {
    "ss58": "dmwtABggtvqJovSnFYi3KX5jCoPs66cZro8et9PJiRk7VGQ1f",
    "metrics": {
      "calamari": "",
      "kusama": ""
    }
  },
  {
    "ss58": "dmxo6FdaDHxPJPdUMDvVzEcqE8UuV2Ve1JURt4jF9efNDyk2o",
    "metrics": {
      "calamari": "",
      "kusama": ""
    }
  },
  {
    "ss58": "dmxRC8PY2FbFhSjsx1RpcqJpiYoZ2ubGR8rAMhW3ocxpWkArh",
    "metrics": {
      "calamari": "",
      "kusama": ""
    }
  }
]
