{
  "balance": {
    "free": "474614431894039966",
    "locked": {
      "fee": "400000000000000000",
      "misc": "400000000000000000"
    },
    "nonce": "6",
    "reserved": "0"
  },
  "location": {
    "city": {
      "name": "Karlsruhe"
    },
    "coordinates": {
      "latitude": "48.9966",
      "longitude": "8.4756"
    },
    "country": {
      "code": "DE",
      "name": "Germany"
    },
    "ip": "202.61.198.200"
  },
  "metrics": {
    "calamari": "https://stats.calamari.migusha.com",
    "kusama": "https://stats.kasuma.migusha.com"
  },
  "session": {
    "aura": "0xa280d1ac65255102b9223e858d93d9f5b53e6e26ec04ea0a14d9c68bb6d5ae20"
  },
  "ss58": "dmvFayQJ9S7BgbHE2kmnoVq9UfdbfwHpZ4d1revJfVA6X9dGR",
  "status": "active"
}
