{
  "at": {
    "hash": "0xcf4662a5e479a000ee0ba18f36c95acadaa1f8a5a3d06330775353269e6dbda4",
    "height": "1299879"
  },
  "nonce": "24",
  "tokenSymbol": "KMA",
  "free": "3454201938042754",
  "reserved": "0",
  "miscFrozen": "2514050000000000",
  "feeFrozen": "0",
  "locks": [
    {
      "id": "0x63616c616d767374",
      "amount": "2514050000000000",
      "reasons": "Misc"
    },
    {
      "id": "0x64656d6f63726163",
      "amount": "2514050000000000",
      "reasons": "Misc"
    }
  ]
}
